dg_itest/__init__.py
dg_itest/servers/__init__.py
dg_itest/servers/dg_servers/__init__.py
dg_itest/servers/dg_servers/dg_after_handler.py
dg_itest/servers/dg_servers/dg_requests.py
dg_itest/servers/dg_servers/dg_singleton.py
dg_itest/servers/file_handler/__init__.py
dg_itest/servers/file_handler/file_handler.py
dg_itest/servers/file_handler/xlsx_handler.py
dg_itest/servers/file_handler/yaml_handler.py
dg_itest/servers/test_handler/__init__.py
dg_itest/servers/test_handler/test_file.py
dg_itest/servers/test_handler/test_item.py
dg_itest/utils/__init__.py
dg_itest/utils/cache.py
dg_itest/utils/conftest.py
dg_itest/utils/diff_helper.py
dg_itest/utils/env_generater.py
dg_itest/utils/file_helper.py
dg_itest/utils/keywords.py
dg_itest/utils/logger.py
dg_itest/utils/replace.py
dg_itest/utils/string_helper.py
dg_itest-0.0.30.dist-info/METADATA
dg_itest-0.0.30.dist-info/WHEEL
dg_itest-0.0.30.dist-info/top_level.txt
dg_itest-0.0.30.dist-info/RECORD
