Metadata-Version: 2.1
Name: dg-itest
Version: 0.0.30
Summary: 接口自动化测试框架
Home-page: https://github.com/yaitza/dg-itest
Author: yaitza
Author-email: yaitza@foxmail.com
License: UNKNOWN
Download-URL: https://github.com/yaitza/dg-itest/releases
Platform: UNKNOWN
Requires-Dist: allure-pytest (==2.13.1)
Requires-Dist: allure-python-commons (==2.13.1)
Requires-Dist: attrs (==23.1.0)
Requires-Dist: black (==25.1.0)
Requires-Dist: bleach (==6.0.0)
Requires-Dist: certifi (==2022.12.7)
Requires-Dist: charset-normalizer (==3.1.0)
Requires-Dist: click (==8.1.8)
Requires-Dist: docutils (==0.19)
Requires-Dist: et-xmlfile (==1.1.0)
Requires-Dist: exceptiongroup (==1.1.1)
Requires-Dist: idna (==3.4)
Requires-Dist: importlib-metadata (==6.6.0)
Requires-Dist: iniconfig (==2.0.0)
Requires-Dist: jaraco.classes (==3.2.3)
Requires-Dist: jsonpath (==0.82)
Requires-Dist: jsonschema (==4.24.0)
Requires-Dist: jsonschema-specifications (==2025.4.1)
Requires-Dist: keyring (==23.13.1)
Requires-Dist: loguru (==0.7.2)
Requires-Dist: markdown-it-py (==2.2.0)
Requires-Dist: mdurl (==0.1.2)
Requires-Dist: more-itertools (==9.1.0)
Requires-Dist: mypy-extensions (==1.0.0)
Requires-Dist: openpyxl (==3.1.2)
Requires-Dist: packaging (==23.1)
Requires-Dist: pathspec (==0.12.1)
Requires-Dist: pkginfo (==1.9.6)
Requires-Dist: platformdirs (==4.3.7)
Requires-Dist: pluggy (==1.6.0)
Requires-Dist: py (==1.11.0)
Requires-Dist: Pygments (==2.15.1)
Requires-Dist: pytest (==8.4.1)
Requires-Dist: python-common-cache (==0.1)
Requires-Dist: PyYAML (==6.0)
Requires-Dist: readme-renderer (==37.3)
Requires-Dist: referencing (==0.36.2)
Requires-Dist: requests (==2.28.2)
Requires-Dist: requests-toolbelt (==0.10.1)
Requires-Dist: rfc3986 (==2.0.0)
Requires-Dist: rich (==13.3.4)
Requires-Dist: rpds-py (==0.25.1)
Requires-Dist: six (==1.16.0)
Requires-Dist: toml (==0.10.2)
Requires-Dist: tomli (==2.0.1)
Requires-Dist: twine (==4.0.2)
Requires-Dist: typing-extensions (==4.12.2)
Requires-Dist: urllib3 (==1.26.15)
Requires-Dist: webencodings (==0.5.1)
Requires-Dist: zipp (==3.15.0)
